RFmodule/RF_max_depth_estimator.py
RFmodule/RF_max_features_estimator.py
RFmodule/RF_min_samples_leaf_estimator.py
RFmodule/RF_min_samples_split_estimator.py
RFmodule/RF_ntree_estimator.py
RFmodule/RF_parameters_estimator_RandomizedSearchCV.py
RFmodule/__init__.py
RFmodule/run_RandomForest_functions.py
rfmodule-0.1.0.dist-info/METADATA
rfmodule-0.1.0.dist-info/WHEEL
rfmodule-0.1.0.dist-info/top_level.txt
rfmodule-0.1.0.dist-info/RECORD
